
demos
tests
doc
