Metadata-Version: 1.0
Name: SPyRE
Version: 0.7.1
Summary: Simple Pythonic Rendering Engine
Home-page: http://pduel.sourceforge.net/spyre
Author: David Keeney
Author-email: dkeeney@travelbyroad.net
License: LPGL
Platform: UNKNOWN
